{
"title": "Lawn Cuts - Outside-In Stitched Pumpkin",
"brand": "Lawn Fawn",
"current_price": 12.49,
"old_price": null,
"currency": "USD",
"product_features": [
  {"Product Code/SKU": "LF2057"},
  {"Location": "FC3-D3-15L"},
  {"Categories": ["15off", "Lawn Fawn dies"]}
],
"short_description": "Lawn Cuts - Outside-In Stitched Pumpkin",
"available_colors": null,
"available_size_variants": "default",
"product_categories": ["Crafting Supplies", "Scrapbooking", "Die Cutting"],
"customer_ratings": null,
"customer_reviews": null,
"similar_or_related_products": [
  "Tonic Studios - Tim Holtz 5 Mini Snips",
  "Universal Crafts - Easy Bow Maker",
  "Solu Crafts - Glitter Mister",
  "Universal Crafts - Ultimate Blending Brush Set",
  "Wendy Vecchi MAKE ART Stay-tion All-In-One Magnetic Surface"
],
"products_recommended_for_me": null
}