{
  "product_title": "Hair Coverage Root Concealer",
  "brand": "Westmore Beauty",
  "current_price": "$29.00 USD",
  "old_price": null,
  "specifications": {
    "material": null,
    "dimensions": "Size: 0.07 oz / 2.1 g"
  },
  "description": "Instantly cover unwanted grays and roots or fill in thinning areas for fuller-looking hair. Our talc-free, water & sweat resistant formula clings to hair strands to absorb excess oil and give you flawless-looking locks that last all day.",
  "sizes": null,
  "colors": [
    "Blond",
    "Honey",
    "Brunette",
    "Dark Brunette",
    "Black",
    "Grey",
    "Red"
  ],
  "variants": null,
  "categories": {
    "general": "Beauty",
    "specific": "Hair Care"
  },
  "breadcrumbs": null,
  "ratings": {
    "5": 0,
    "4": 0,
    "3": 0,
    "2": 0,
    "1": 0
  },
  "opinions": [],
  "number_available_items": null,
  "similar_products": null,
  "products_i_may_also_like": null,
  "related_products": null,
  "recommended_for_me": null
}