{
  "product_title": "ALAVIS Sanicell 60tab.",
  "brand": "Alavis",
  "current_price": 103.61,
  "old_price": 189.00,
  "specifications": {
    "material": "Suplement weterynaryjny",
    "dimensions": "60 kapsułek"
  },
  "description": "Suplement ten regeneruje wątrobę, wzmocnienie odporności, ochrona przed chorobami nowotworowymi.",
  "sizes": [
    "uniwersalny"
  ],
  "colors": null,
  "variants": null,
  "categories": [
    {
      "general": "Suplementy weterynaryjne",
      "specific": "Suplementy na wątrobę"
    }
  ],
  "breadcrumbs": null,
  "ratings": {
    "5": 0,
    "4": 0,
    "3": 0,
    "2": 0,
    "1": 0
  },
  "opinions": null,
  "number_available_items": null,
  "similar_products": null,
  "products_i_may_also_like": null,
  "related_products": null,
  "recommended_for_me": null
}