{
"title": "REGENERUM - szampon regenerujący do włosów, 150ml",
"brand": "Aflofarm",
"current_price": {"price": 23.00, "currency": "PLN"},
"old_price": null,
"product_features": [
  {"feature": "Delikatnie oczyszcza włosy i skórę głowy"},
  {"feature": "Nawilża i odżywia delikatny skalp, dzięki zawartości wyciągu z aloesu"},
  {"feature": "Wzmacnia, uelastycznia i wygładza włosy, zapobiegając w ten sposób plątaniu"},
  {"feature": "Naprawia uszkodzenia powstałe w czasie stylizacji lub pod wpływem niekorzystnych czynników zewnętrznych"},
  {"feature": "Ułatwia rozczesywanie oraz układanie włosów"},
  {"feature": "Kompleks z brązowych alg - sprawia, że włosy stają się bardziej odporne na działanie wysokiej temperatury, czynników zewnętrznych i substancji chemicznych"},
  {"feature": "Hydrolizat keratyny - wbudowuje się w strukturę włosa, ułatwia rozczesywanie"},
  {"feature": "Prowitamina B5 - wzmacnia włosy i zapobiega ich rozdwajaniu"},
  {"feature": "Wyciąg z aloesu - intensywnie i długotrwale nawilża"},
  {"feature": "Pojemność: 150 ml"}
],
"short_description": "Szampon regenerujący do włosów REGENERUM intensywnie wzmacnia i regeneruje włosy.",
"all_colors_variants": null,
"size_variants": null,
"product_categories": ["Pielęgnacja Włosów", "Szampony"],
"customer_ratings": {"average_rating": 0.0, "number_of_ratings": 0},
"customer_reviews": null,
"similar_or_related_products": null,
"products_recommended_for_me": null
}