{
  "title": "Tully Bracelet (Vermeil)",
  "brand": "null",
  "current_price": {
    "price": 72.0,
    "currency": "USD"
  },
  "old_price": null,
  "specifications": [
    {
      "specification_name": "material",
      "specification_value": "Vermeil: A thick layer of 18K solid gold on sterling silver."
    },
    {
      "specification_name": "dimensions",
      "specification_value": "6\" length + 1\" extension"
    },
    {
      "specification_name": "other_features",
      "specification_value": [
        {
          "feature_name": "weight",
          "feature_value": "0.03 oz"
        },
        {
          "feature_name": "clasp type",
          "feature_value": "Lobster clasp closure"
        },
        {
          "feature_name": "stones",
          "feature_value": "Moissanite stones"
        },
        {
          "feature_name": "hypoallergenic",
          "feature_value": "Hypoallergenic, nickel free"
        }
      ]
    }
  ],
  "description": "A delicate gold bracelet adorned with a trio of gems. This simple style is just what you need to add a touch of luxe to your everyday look. Shown here with the Meja Pendant and Demi Studs. Vermeil Collection. This demi-fine jewelry collection features styles crafted with a thick layer of 18K gold on sterling silver, and set with Moissanite, diamond-like stones. 18K gold has a warmer, golden-yellow hue compared to 14K.",
  "sizes": null,
  "colors": null,
  "variants": null,
  "categories": null,
  "general_category": null,
  "specific_category": null,
  "breadcrumbs": null,
  "customer_ratings": null,
  "number_of_available_items": null,
  "similar_products": null,
  "products_I_may_also_like": null,
  "related_products": null,
  "recommended_for_me": null
}